setup.py
csv2dict/__init__.py
csv2dict/csvdictmaker.py
csv2dict.egg-info/PKG-INFO
csv2dict.egg-info/SOURCES.txt
csv2dict.egg-info/dependency_links.txt
csv2dict.egg-info/not-zip-safe
csv2dict.egg-info/top_level.txt