Metadata-Version: 1.0
Name: csv2dict
Version: 1.0
Summary: Read a CSV file into a dict
Home-page: UNKNOWN
Author: Aureus Analytics
Author-email: raj@aureusanalytics.com
License: MIT
Platform: UNKNOWN
